jellyfish/__init__.py
jellyfish/_openapi_client/__init__.py
jellyfish/_openapi_client/api/__init__.py
jellyfish/_openapi_client/api/health/__init__.py
jellyfish/_openapi_client/api/health/healthcheck.py
jellyfish/_openapi_client/api/hls/__init__.py
jellyfish/_openapi_client/api/hls/get_hls_content.py
jellyfish/_openapi_client/api/recording/__init__.py
jellyfish/_openapi_client/api/recording/delete_recording.py
jellyfish/_openapi_client/api/recording/get_recording_content.py
jellyfish/_openapi_client/api/recording/get_recordings.py
jellyfish/_openapi_client/api/room/__init__.py
jellyfish/_openapi_client/api/room/add_component.py
jellyfish/_openapi_client/api/room/add_peer.py
jellyfish/_openapi_client/api/room/create_room.py
jellyfish/_openapi_client/api/room/delete_component.py
jellyfish/_openapi_client/api/room/delete_peer.py
jellyfish/_openapi_client/api/room/delete_room.py
jellyfish/_openapi_client/api/room/get_all_rooms.py
jellyfish/_openapi_client/api/room/get_room.py
jellyfish/_openapi_client/api/room/subscribe_to.py
jellyfish/_openapi_client/api/sip/__init__.py
jellyfish/_openapi_client/api/sip/dial.py
jellyfish/_openapi_client/api/sip/end_call.py
jellyfish/_openapi_client/client.py
jellyfish/_openapi_client/errors.py
jellyfish/_openapi_client/models/__init__.py
jellyfish/_openapi_client/models/add_component_json_body.py
jellyfish/_openapi_client/models/add_peer_json_body.py
jellyfish/_openapi_client/models/component_details_response.py
jellyfish/_openapi_client/models/component_file.py
jellyfish/_openapi_client/models/component_hls.py
jellyfish/_openapi_client/models/component_options_file.py
jellyfish/_openapi_client/models/component_options_hls.py
jellyfish/_openapi_client/models/component_options_hls_subscribe_mode.py
jellyfish/_openapi_client/models/component_options_recording.py
jellyfish/_openapi_client/models/component_options_recording_subscribe_mode.py
jellyfish/_openapi_client/models/component_options_rtsp.py
jellyfish_server_sdk-0.4.0.dist-info/METADATA
jellyfish_server_sdk-0.4.0.dist-info/WHEEL
jellyfish_server_sdk-0.4.0.dist-info/entry_points.txt
jellyfish_server_sdk-0.4.0.dist-info/RECORD
