Metadata-Version: 2.1
Name: jellyfish-server-sdk
Version: 0.4.0
Summary: Python server SDK for the Jellyfish media server
Home-page: https://github.com/jellyfish-dev/python-server-sdk
License: Apache-2.0
Author: Jellyfish Team
Requires-Python: >=3.8,<4.0
Classifier: License :: OSI Approved :: Apache Software License
Classifier: Programming Language :: Python :: 3
Classifier: Programming Language :: Python :: 3.8
Classifier: Programming Language :: Python :: 3.9
Classifier: Programming Language :: Python :: 3.10
Classifier: Programming Language :: Python :: 3.11
Classifier: Programming Language :: Python :: 3.12
Requires-Dist: aenum (>=3.1.15,<4.0.0)
Requires-Dist: attrs (>=21.3.0)
Requires-Dist: betterproto (==2.0.0b6)
Requires-Dist: httpx (>=0.20.0,<0.26.0)
Requires-Dist: python-dateutil (>=2.8.2,<3.0.0)
Requires-Dist: urllib3 (>=1.25.3,<2)
Requires-Dist: websockets (>=11.0.3,<12.0.0)
Project-URL: Documentation, https://jellyfish-dev.github.io/python-server-sdk/jellyfish
